agrossuite/Qt6Core.dll
agrossuite/Qt6Core5Compat.dll
agrossuite/Qt6Xml.dll
agrossuite/__init__.py
agrossuite/_agros.cp312-win_amd64.pyd
agrossuite/agros.py
agrossuite/agros_3rdparty_triangle.dll
agrossuite/agros_library.dll
agrossuite/agros_python.dll
agrossuite/tbb12.dll
agrossuite/tools.py
agrossuite/xerces-c_3_1.dll
agrossuite/zlib.dll
agrossuite/lib/Qt6Core.dll
agrossuite/lib/Qt6Core5Compat.dll
agrossuite/lib/Qt6Xml.dll
agrossuite/lib/agros_3rdparty_triangle.dll
agrossuite/lib/agros_library.dll
agrossuite/lib/agros_plugin_acoustic.dll
agrossuite/lib/agros_plugin_current.dll
agrossuite/lib/agros_plugin_elasticity.dll
agrossuite/lib/agros_plugin_electrostatic.dll
agrossuite/lib/agros_plugin_flow.dll
agrossuite/lib/agros_plugin_heat.dll
agrossuite/lib/agros_plugin_magnetic.dll
agrossuite/lib/agros_plugin_rf_te.dll
agrossuite/lib/agros_plugin_rf_tm.dll
agrossuite/lib/agros_python.dll
agrossuite/lib/libifcoremd.dll
agrossuite/lib/libmmd.dll
agrossuite/lib/solver_plugin_EXTERNAL.dll
agrossuite/lib/solver_plugin_MUMPS.dll
agrossuite/lib/solver_plugin_amgcl.dll
agrossuite/lib/tbb12.dll
agrossuite/lib/zlib.dll
agrossuite/tests/__init__.py
agrossuite/tests/scenario.py
agrossuite/tests/test_adaptivity.py
agrossuite/tests/test_coupled_basic_problems.py
agrossuite/tests/test_coupled_unrealistic_problems.py
agrossuite/tests/test_field_acoustic.py
agrossuite/tests/test_field_current.py
agrossuite/tests/test_field_elasticity.py
agrossuite/tests/test_field_electrostatic.py
agrossuite/tests/test_field_flow.py
agrossuite/tests/test_field_heat.py
agrossuite/tests/test_field_magnetic_harmonic.py
agrossuite/tests/test_field_magnetic_steady.py
agrossuite/tests/test_field_magnetic_transient.py
agrossuite/tests/test_field_rf_te.py
agrossuite/tests/test_field_rf_tm.py
agrossuite/tests/test_matrix_solvers.py
agrossuite/tests/test_optilab.py
agrossuite-2026.1.31.1438.dist-info/METADATA
agrossuite-2026.1.31.1438.dist-info/WHEEL
agrossuite-2026.1.31.1438.dist-info/top_level.txt
agrossuite-2026.1.31.1438.dist-info/RECORD
